{"test_class": {"identifier": "BitUtilTest", "superclass": "", "interfaces": "", "fields": [], "file": "util/src/test/java/com/liux/android/util/BitUtilTest.java"}, "test_case": {"identifier": "int2Bin", "parameters": "()", "modifiers": "@Test public", "return": "void", "body": "@Test\n    public void int2Bin() {\n        assertEquals(\"111_1111_1111_1111_1111_1111_1111_1111\".replace(\"_\", \"\"), BitUtil.int2Bin(2147483647));\n    }", "signature": "void int2Bin()", "full_signature": "@Test public void int2Bin()", "class_method_signature": "BitUtilTest.int2Bin()", "testcase": true, "constructor": false, "invocations": ["assertEquals", "replace", "int2Bin"]}, "focal_class": {"identifier": "BitUtil", "superclass": "", "interfaces": "", "fields": [], "methods": [{"identifier": "int2Bin", "parameters": "(int source)", "modifiers": "public static", "return": "String", "signature": "String int2Bin(int source)", "full_signature": "public static String int2Bin(int source)", "class_method_signature": "BitUtil.int2Bin(int source)", "testcase": false, "constructor": false}, {"identifier": "bin2Int", "parameters": "(String source)", "modifiers": "public static", "return": "int", "signature": "int bin2Int(String source)", "full_signature": "public static int bin2Int(String source)", "class_method_signature": "BitUtil.bin2Int(String source)", "testcase": false, "constructor": false}, {"identifier": "long2Bin", "parameters": "(long source)", "modifiers": "public static", "return": "String", "signature": "String long2Bin(long source)", "full_signature": "public static String long2Bin(long source)", "class_method_signature": "BitUtil.long2Bin(long source)", "testcase": false, "constructor": false}, {"identifier": "bin2Long", "parameters": "(String source)", "modifiers": "public static", "return": "long", "signature": "long bin2Long(String source)", "full_signature": "public static long bin2Long(String source)", "class_method_signature": "BitUtil.bin2Long(String source)", "testcase": false, "constructor": false}, {"identifier": "getIntBit", "parameters": "(int source, int pos)", "modifiers": "public static", "return": "boolean", "signature": "boolean getIntBit(int source, int pos)", "full_signature": "public static boolean getIntBit(int source, int pos)", "class_method_signature": "BitUtil.getIntBit(int source, int pos)", "testcase": false, "constructor": false}, {"identifier": "setIntBit", "parameters": "(int source, int pos, boolean value)", "modifiers": "public static", "return": "int", "signature": "int setIntBit(int source, int pos, boolean value)", "full_signature": "public static int setIntBit(int source, int pos, boolean value)", "class_method_signature": "BitUtil.setIntBit(int source, int pos, boolean value)", "testcase": false, "constructor": false}, {"identifier": "getLongBit", "parameters": "(long source, int pos)", "modifiers": "public static", "return": "boolean", "signature": "boolean getLongBit(long source, int pos)", "full_signature": "public static boolean getLongBit(long source, int pos)", "class_method_signature": "BitUtil.getLongBit(long source, int pos)", "testcase": false, "constructor": false}, {"identifier": "setLongBit", "parameters": "(long source, int pos, boolean value)", "modifiers": "public static", "return": "long", "signature": "long setLongBit(long source, int pos, boolean value)", "full_signature": "public static long setLongBit(long source, int pos, boolean value)", "class_method_signature": "BitUtil.setLongBit(long source, int pos, boolean value)", "testcase": false, "constructor": false}], "file": "util/src/main/java/com/liux/android/util/BitUtil.java"}, "focal_method": {"identifier": "int2Bin", "parameters": "(int source)", "modifiers": "public static", "return": "String", "body": "public static String int2Bin(int source) {\n        return Integer.toBinaryString(source);\n    }", "signature": "String int2Bin(int source)", "full_signature": "public static String int2Bin(int source)", "class_method_signature": "BitUtil.int2Bin(int source)", "testcase": false, "constructor": false, "invocations": ["toBinaryString"]}, "repository": {"repo_id": 119475284, "url": "https://github.com/lx0758/Android-Librarys", "language": "Java", "is_fork": false, "fork_count": 3, "stargazer_count": 6, "size": 6354, "license": "licensed"}}