{"test_class": {"identifier": "RaptorInterfaceUtilsTest", "superclass": "", "interfaces": "", "fields": [], "file": "raptor-springboot/src/test/java/com/ppdai/framework/raptor/spring/utils/RaptorInterfaceUtilsTest.java"}, "test_case": {"identifier": "findMethod", "parameters": "()", "modifiers": "@Test public", "return": "void", "body": "@Test\n    public void findMethod() {\n        Method method = ReflectionUtils.findMethod(MoreServiceImpl.class, \"testGet2\", HelloRequest.class);\n        String interfaceName = RaptorInterfaceUtils.getInterfaceName(MoreServiceImpl.class, method);\n        System.out.println(interfaceName);\n        Assert.assertEquals(MoreService.class.getName(), interfaceName);\n    }", "signature": "void findMethod()", "full_signature": "@Test public void findMethod()", "class_method_signature": "RaptorInterfaceUtilsTest.findMethod()", "testcase": true, "constructor": false, "invocations": ["findMethod", "getInterfaceName", "println", "assertEquals", "getName"]}, "focal_class": {"identifier": "RaptorInterfaceUtils", "superclass": "", "interfaces": "", "fields": [{"original_string": "private final static Map<String, Class<?>> METHOD_INTERFACE_CACHE = new ConcurrentHashMap<>();", "modifier": "private final static", "type": "Map<String, Class<?>>", "declarator": "METHOD_INTERFACE_CACHE = new ConcurrentHashMap<>()", "var_name": "METHOD_INTERFACE_CACHE"}], "methods": [{"identifier": "getInterfaceName", "parameters": "(Class<?> type, Method method)", "modifiers": "public static", "return": "String", "signature": "String getInterfaceName(Class<?> type, Method method)", "full_signature": "public static String getInterfaceName(Class<?> type, Method method)", "class_method_signature": "RaptorInterfaceUtils.getInterfaceName(Class<?> type, Method method)", "testcase": false, "constructor": false}, {"identifier": "getInterfaceClass", "parameters": "(Class<?> type, Method method)", "modifiers": "public static", "return": "Class<?>", "signature": "Class<?> getInterfaceClass(Class<?> type, Method method)", "full_signature": "public static Class<?> getInterfaceClass(Class<?> type, Method method)", "class_method_signature": "RaptorInterfaceUtils.getInterfaceClass(Class<?> type, Method method)", "testcase": false, "constructor": false}, {"identifier": "findRaptorInterfaces", "parameters": "(Class<?> clazz)", "modifiers": "public static", "return": "List<Class<?>>", "signature": "List<Class<?>> findRaptorInterfaces(Class<?> clazz)", "full_signature": "public static List<Class<?>> findRaptorInterfaces(Class<?> clazz)", "class_method_signature": "RaptorInterfaceUtils.findRaptorInterfaces(Class<?> clazz)", "testcase": false, "constructor": false}, {"identifier": "getMethodSignature", "parameters": "(Method method)", "modifiers": "public static", "return": "String", "signature": "String getMethodSignature(Method method)", "full_signature": "public static String getMethodSignature(Method method)", "class_method_signature": "RaptorInterfaceUtils.getMethodSignature(Method method)", "testcase": false, "constructor": false}], "file": "raptor-springboot/src/main/java/com/ppdai/framework/raptor/spring/utils/RaptorInterfaceUtils.java"}, "focal_method": {"identifier": "getInterfaceName", "parameters": "(Class<?> type, Method method)", "modifiers": "public static", "return": "String", "body": "public static String getInterfaceName(Class<?> type, Method method) {\n        Class<?> interfaceClass = getInterfaceClass(type, method);\n        return interfaceClass == null ? null : interfaceClass.getName();\n    }", "signature": "String getInterfaceName(Class<?> type, Method method)", "full_signature": "public static String getInterfaceName(Class<?> type, Method method)", "class_method_signature": "RaptorInterfaceUtils.getInterfaceName(Class<?> type, Method method)", "testcase": false, "constructor": false, "invocations": ["getInterfaceClass", "getName"]}, "repository": {"repo_id": 129712230, "url": "https://github.com/geekshop/raptor", "language": "Java", "is_fork": false, "fork_count": 42, "stargazer_count": 139, "size": 23351, "license": "licensed"}}