{"test_class": {"identifier": "ColumnsMaskTest", "superclass": "", "interfaces": "", "fields": [], "file": "fast-ftrl-proximal/src/test/java/io/scaledml/core/inputformats/ColumnsMaskTest.java"}, "test_case": {"identifier": "testParse3", "parameters": "()", "modifiers": "@Test public", "return": "void", "body": "@Test\n    public void testParse3() {\n        ColumnsMask mask = new ColumnsMask(\"ilcccccnnnnn\");\n        assertEquals(ColumnType.ID, mask.getCategory(0));\n        assertEquals(ColumnType.LABEL, mask.getCategory(1));\n        assertEquals(ColumnType.CATEGORICAL, mask.getCategory(4));\n        assertEquals(ColumnType.NUMERICAL, mask.getCategory(1024));\n    }", "signature": "void testParse3()", "full_signature": "@Test public void testParse3()", "class_method_signature": "ColumnsMaskTest.testParse3()", "testcase": true, "constructor": false, "invocations": ["assertEquals", "getCategory", "assertEquals", "getCategory", "assertEquals", "getCategory", "assertEquals", "getCategory"]}, "focal_class": {"identifier": "ColumnsMask", "superclass": "", "interfaces": "", "fields": [{"original_string": "private final String str;", "modifier": "private final", "type": "String", "declarator": "str", "var_name": "str"}, {"original_string": "private ArrayList<ColumnType> columns = new ArrayList<>();", "modifier": "private", "type": "ArrayList<ColumnType>", "declarator": "columns = new ArrayList<>()", "var_name": "columns"}], "methods": [{"identifier": "ColumnsMask", "parameters": "(String str)", "modifiers": "public", "return": "", "signature": " ColumnsMask(String str)", "full_signature": "public  ColumnsMask(String str)", "class_method_signature": "ColumnsMask.ColumnsMask(String str)", "testcase": false, "constructor": true}, {"identifier": "charToColumnType", "parameters": "(char c)", "modifiers": "private static", "return": "ColumnType", "signature": "ColumnType charToColumnType(char c)", "full_signature": "private static ColumnType charToColumnType(char c)", "class_method_signature": "ColumnsMask.charToColumnType(char c)", "testcase": false, "constructor": false}, {"identifier": "toString", "parameters": "()", "modifiers": "@Override public", "return": "String", "signature": "String toString()", "full_signature": "@Override public String toString()", "class_method_signature": "ColumnsMask.toString()", "testcase": false, "constructor": false}, {"identifier": "getCategory", "parameters": "(int colNumber)", "modifiers": "public", "return": "ColumnType", "signature": "ColumnType getCategory(int colNumber)", "full_signature": "public ColumnType getCategory(int colNumber)", "class_method_signature": "ColumnsMask.getCategory(int colNumber)", "testcase": false, "constructor": false}], "file": "fast-ftrl-proximal/src/main/java/io/scaledml/core/inputformats/ColumnsMask.java"}, "focal_method": {"identifier": "getCategory", "parameters": "(int colNumber)", "modifiers": "public", "return": "ColumnType", "body": "public ColumnType getCategory(int colNumber) {\n        if (colNumber < columns.size()) {\n            return columns.get(colNumber);\n        }\n        return columns.get(columns.size() - 1);\n    }", "signature": "ColumnType getCategory(int colNumber)", "full_signature": "public ColumnType getCategory(int colNumber)", "class_method_signature": "ColumnsMask.getCategory(int colNumber)", "testcase": false, "constructor": false, "invocations": ["size", "get", "get", "size"]}, "repository": {"repo_id": 32203040, "url": "https://github.com/scaled-ml/Scaled-ML", "language": "Java", "is_fork": false, "fork_count": 5, "stargazer_count": 10, "size": 18435, "license": "licensed"}}