{"test_class": {"identifier": "CarpaccioHelperTest", "superclass": "", "interfaces": "", "fields": [], "file": "carpaccio/src/test/java/com/github/florent37/carpaccio/CarpaccioHelperTest.java"}, "test_case": {"identifier": "testStringToNumber", "parameters": "()", "modifiers": "@Test public", "return": "void", "body": "@Test\n    public void testStringToNumber() throws Exception {\n        assertEquals(3,CarpaccioHelper.stringToNumber(\"3\",int.class));\n        assertEquals(3l,CarpaccioHelper.stringToNumber(\"3\",long.class));\n        assertEquals(3.f,CarpaccioHelper.stringToNumber(\"3\",float.class));\n        assertEquals(3.d,CarpaccioHelper.stringToNumber(\"3\",double.class));\n\n        assertEquals(Integer.valueOf(3),CarpaccioHelper.stringToNumber(\"3\",Integer.class));\n        assertEquals(Long.valueOf(3),CarpaccioHelper.stringToNumber(\"3\",Long.class));\n        assertEquals(Float.valueOf(3),CarpaccioHelper.stringToNumber(\"3\",Float.class));\n        assertEquals(Double.valueOf(3),CarpaccioHelper.stringToNumber(\"3\",Double.class));\n\n        assertEquals(null,CarpaccioHelper.stringToNumber(null,Integer.class));\n        assertNull(CarpaccioHelper.stringToNumber(\"3\",String.class));\n    }", "signature": "void testStringToNumber()", "full_signature": "@Test public void testStringToNumber()", "class_method_signature": "CarpaccioHelperTest.testStringToNumber()", "testcase": true, "constructor": false, "invocations": ["assertEquals", "stringToNumber", "assertEquals", "stringToNumber", "assertEquals", "stringToNumber", "assertEquals", "stringToNumber", "assertEquals", "valueOf", "stringToNumber", "assertEquals", "valueOf", "stringToNumber", "assertEquals", "valueOf", "stringToNumber", "assertEquals", "valueOf", "stringToNumber", "assertEquals", "stringToNumber", "assertNull", "stringToNumber"]}, "focal_class": {"identifier": "CarpaccioHelper", "superclass": "", "interfaces": "", "fields": [{"original_string": "public static String TAG = \"CarpaccioHelper\";", "modifier": "public static", "type": "String", "declarator": "TAG = \"CarpaccioHelper\"", "var_name": "TAG"}, {"original_string": "public static boolean LOG_FAILURES = false;", "modifier": "public static", "type": "boolean", "declarator": "LOG_FAILURES = false", "var_name": "LOG_FAILURES"}, {"original_string": "protected static LruCache<String, Class> classesCache = new LruCache<>(15);", "modifier": "protected static", "type": "LruCache<String, Class>", "declarator": "classesCache = new LruCache<>(15)", "var_name": "classesCache"}], "methods": [{"identifier": "construct", "parameters": "(String name)", "modifiers": "public static", "return": "Object", "signature": "Object construct(String name)", "full_signature": "public static Object construct(String name)", "class_method_signature": "CarpaccioHelper.construct(String name)", "testcase": false, "constructor": false}, {"identifier": "getClassesWithHeaderClass", "parameters": "(Object[] args, Class headerClass)", "modifiers": "public static", "return": "Class[]", "signature": "Class[] getClassesWithHeaderClass(Object[] args, Class headerClass)", "full_signature": "public static Class[] getClassesWithHeaderClass(Object[] args, Class headerClass)", "class_method_signature": "CarpaccioHelper.getClassesWithHeaderClass(Object[] args, Class headerClass)", "testcase": false, "constructor": false}, {"identifier": "getClasses", "parameters": "(Object[] args)", "modifiers": "public static", "return": "Class[]", "signature": "Class[] getClasses(Object[] args)", "full_signature": "public static Class[] getClasses(Object[] args)", "class_method_signature": "CarpaccioHelper.getClasses(Object[] args)", "testcase": false, "constructor": false}, {"identifier": "getArgumentsWithView", "parameters": "(View view, Class[] parametersType, Object[] args)", "modifiers": "public static", "return": "Object[]", "signature": "Object[] getArgumentsWithView(View view, Class[] parametersType, Object[] args)", "full_signature": "public static Object[] getArgumentsWithView(View view, Class[] parametersType, Object[] args)", "class_method_signature": "CarpaccioHelper.getArgumentsWithView(View view, Class[] parametersType, Object[] args)", "testcase": false, "constructor": false}, {"identifier": "getFunctionName", "parameters": "(String tag)", "modifiers": "public static", "return": "String", "signature": "String getFunctionName(String tag)", "full_signature": "public static String getFunctionName(String tag)", "class_method_signature": "CarpaccioHelper.getFunctionName(String tag)", "testcase": false, "constructor": false}, {"identifier": "getAttributes", "parameters": "(String tag)", "modifiers": "public static", "return": "String[]", "signature": "String[] getAttributes(String tag)", "full_signature": "public static String[] getAttributes(String tag)", "class_method_signature": "CarpaccioHelper.getAttributes(String tag)", "testcase": false, "constructor": false}, {"identifier": "removeTag", "parameters": "(View view, String actionName)", "modifiers": "public static", "return": "Object", "signature": "Object removeTag(View view, String actionName)", "full_signature": "public static Object removeTag(View view, String actionName)", "class_method_signature": "CarpaccioHelper.removeTag(View view, String actionName)", "testcase": false, "constructor": false}, {"identifier": "trim", "parameters": "(String[] strings)", "modifiers": "public static", "return": "String[]", "signature": "String[] trim(String[] strings)", "full_signature": "public static String[] trim(String[] strings)", "class_method_signature": "CarpaccioHelper.trim(String[] strings)", "testcase": false, "constructor": false}, {"identifier": "findObjectWithThisMethod", "parameters": "(List<Object> objects, String function, int numberOfParams)", "modifiers": "public static", "return": "ObjectAndMethod", "signature": "ObjectAndMethod findObjectWithThisMethod(List<Object> objects, String function, int numberOfParams)", "full_signature": "public static ObjectAndMethod findObjectWithThisMethod(List<Object> objects, String function, int numberOfParams)", "class_method_signature": "CarpaccioHelper.findObjectWithThisMethod(List<Object> objects, String function, int numberOfParams)", "testcase": false, "constructor": false}, {"identifier": "callFunction", "parameters": "(Object object, String name, View view, Object[] args)", "modifiers": "public static", "return": "Method", "signature": "Method callFunction(Object object, String name, View view, Object[] args)", "full_signature": "public static Method callFunction(Object object, String name, View view, Object[] args)", "class_method_signature": "CarpaccioHelper.callFunction(Object object, String name, View view, Object[] args)", "testcase": false, "constructor": false}, {"identifier": "callMethod", "parameters": "(Object object, Method method, String name, View view, Object[] args)", "modifiers": "public static", "return": "Method", "signature": "Method callMethod(Object object, Method method, String name, View view, Object[] args)", "full_signature": "public static Method callMethod(Object object, Method method, String name, View view, Object[] args)", "class_method_signature": "CarpaccioHelper.callMethod(Object object, Method method, String name, View view, Object[] args)", "testcase": false, "constructor": false}, {"identifier": "callFunction", "parameters": "(Object object, String name)", "modifiers": "public static", "return": "T", "signature": "T callFunction(Object object, String name)", "full_signature": "public static T callFunction(Object object, String name)", "class_method_signature": "CarpaccioHelper.callFunction(Object object, String name)", "testcase": false, "constructor": false}, {"identifier": "callFunction", "parameters": "(Object object, String name, Object[] args)", "modifiers": "public static", "return": "T", "signature": "T callFunction(Object object, String name, Object[] args)", "full_signature": "public static T callFunction(Object object, String name, Object[] args)", "class_method_signature": "CarpaccioHelper.callFunction(Object object, String name, Object[] args)", "testcase": false, "constructor": false}, {"identifier": "stringToInt", "parameters": "(String s)", "modifiers": "public static", "return": "Integer", "signature": "Integer stringToInt(String s)", "full_signature": "public static Integer stringToInt(String s)", "class_method_signature": "CarpaccioHelper.stringToInt(String s)", "testcase": false, "constructor": false}, {"identifier": "stringToDouble", "parameters": "(String s)", "modifiers": "public static", "return": "Double", "signature": "Double stringToDouble(String s)", "full_signature": "public static Double stringToDouble(String s)", "class_method_signature": "CarpaccioHelper.stringToDouble(String s)", "testcase": false, "constructor": false}, {"identifier": "stringToLong", "parameters": "(String s)", "modifiers": "public static", "return": "Long", "signature": "Long stringToLong(String s)", "full_signature": "public static Long stringToLong(String s)", "class_method_signature": "CarpaccioHelper.stringToLong(String s)", "testcase": false, "constructor": false}, {"identifier": "stringToFloat", "parameters": "(String s)", "modifiers": "public static", "return": "Float", "signature": "Float stringToFloat(String s)", "full_signature": "public static Float stringToFloat(String s)", "class_method_signature": "CarpaccioHelper.stringToFloat(String s)", "testcase": false, "constructor": false}, {"identifier": "isNumber", "parameters": "(Class destinationClass)", "modifiers": "public static", "return": "boolean", "signature": "boolean isNumber(Class destinationClass)", "full_signature": "public static boolean isNumber(Class destinationClass)", "class_method_signature": "CarpaccioHelper.isNumber(Class destinationClass)", "testcase": false, "constructor": false}, {"identifier": "stringToNumber", "parameters": "(String s, Class destinationClass)", "modifiers": "public static", "return": "Object", "signature": "Object stringToNumber(String s, Class destinationClass)", "full_signature": "public static Object stringToNumber(String s, Class destinationClass)", "class_method_signature": "CarpaccioHelper.stringToNumber(String s, Class destinationClass)", "testcase": false, "constructor": false}, {"identifier": "findParentOfClass", "parameters": "(View view, Class<T> theClass)", "modifiers": "public static", "return": "T", "signature": "T findParentOfClass(View view, Class<T> theClass)", "full_signature": "public static T findParentOfClass(View view, Class<T> theClass)", "class_method_signature": "CarpaccioHelper.findParentOfClass(View view, Class<T> theClass)", "testcase": false, "constructor": false}, {"identifier": "findParentCarpaccio", "parameters": "(View view)", "modifiers": "public static", "return": "Carpaccio", "signature": "Carpaccio findParentCarpaccio(View view)", "full_signature": "public static Carpaccio findParentCarpaccio(View view)", "class_method_signature": "CarpaccioHelper.findParentCarpaccio(View view)", "testcase": false, "constructor": false}, {"identifier": "registerToParentCarpaccio", "parameters": "(View view)", "modifiers": "public static", "return": "Carpaccio", "signature": "Carpaccio registerToParentCarpaccio(View view)", "full_signature": "public static Carpaccio registerToParentCarpaccio(View view)", "class_method_signature": "CarpaccioHelper.registerToParentCarpaccio(View view)", "testcase": false, "constructor": false}], "file": "carpaccio/src/main/java/com/github/florent37/carpaccio/CarpaccioHelper.java"}, "focal_method": {"identifier": "stringToNumber", "parameters": "(String s, Class destinationClass)", "modifiers": "public static", "return": "Object", "body": "public static Object stringToNumber(String s, Class destinationClass) {\n        if (Integer.class.equals(destinationClass))\n            return stringToInt(s);\n        else if (destinationClass.getName().equals(\"int\"))\n            return stringToInt(s);\n        else if (Float.class.equals(destinationClass))\n            return stringToFloat(s);\n        else if (destinationClass.getName().equals(\"float\"))\n            return stringToFloat(s);\n        else if (Long.class.equals(destinationClass))\n            return stringToLong(s);\n        else if (destinationClass.getName().equals(\"long\"))\n            return stringToLong(s);\n        else if (Double.class.equals(destinationClass))\n            return stringToDouble(s);\n        else if (destinationClass.getName().equals(\"double\"))\n            return stringToDouble(s);\n        else\n            return null;\n    }", "signature": "Object stringToNumber(String s, Class destinationClass)", "full_signature": "public static Object stringToNumber(String s, Class destinationClass)", "class_method_signature": "CarpaccioHelper.stringToNumber(String s, Class destinationClass)", "testcase": false, "constructor": false, "invocations": ["equals", "stringToInt", "equals", "getName", "stringToInt", "equals", "stringToFloat", "equals", "getName", "stringToFloat", "equals", "stringToLong", "equals", "getName", "stringToLong", "equals", "stringToDouble", "equals", "getName", "stringToDouble"]}, "repository": {"repo_id": 39472279, "url": "https://github.com/florent37/Carpaccio", "language": "Java", "is_fork": false, "fork_count": 72, "stargazer_count": 427, "size": 31263, "license": "licensed"}}