{"test_class": {"identifier": "FSStorageAgentTest", "superclass": "", "interfaces": "", "fields": [{"original_string": "@Rule\n  public TestMeta testMeta = new TestMeta();", "modifier": "@Rule\n  public", "type": "TestMeta", "declarator": "testMeta = new TestMeta()", "var_name": "testMeta"}], "file": "common/src/test/java/com/datatorrent/common/util/FSStorageAgentTest.java"}, "test_case": {"identifier": "testSave", "parameters": "()", "modifiers": "@Test public", "return": "void", "body": "@Test\n  public void testSave() throws IOException\n  {\n    Map<Integer, String> data = Maps.newHashMap();\n    data.put(1, \"one\");\n    data.put(2, \"two\");\n    data.put(3, \"three\");\n    testMeta.storageAgent.save(data, 1, 1);\n    @SuppressWarnings(\"unchecked\")\n    Map<Integer, String> decoded = (Map<Integer, String>)testMeta.storageAgent.load(1, 1);\n    Assert.assertEquals(\"dataOf1\", data, decoded);\n  }", "signature": "void testSave()", "full_signature": "@Test public void testSave()", "class_method_signature": "FSStorageAgentTest.testSave()", "testcase": true, "constructor": false, "invocations": ["newHashMap", "put", "put", "put", "save", "load", "assertEquals"]}, "focal_class": {"identifier": "FSStorageAgent", "superclass": "", "interfaces": "implements StorageAgent, Serializable", "fields": [{"original_string": "public static final String TMP_FILE = \"_tmp\";", "modifier": "public static final", "type": "String", "declarator": "TMP_FILE = \"_tmp\"", "var_name": "TMP_FILE"}, {"original_string": "protected static final String STATELESS_CHECKPOINT_WINDOW_ID = Long.toHexString(Stateless.WINDOW_ID);", "modifier": "protected static final", "type": "String", "declarator": "STATELESS_CHECKPOINT_WINDOW_ID = Long.toHexString(Stateless.WINDOW_ID)", "var_name": "STATELESS_CHECKPOINT_WINDOW_ID"}, {"original_string": "public final String path;", "modifier": "public final", "type": "String", "declarator": "path", "var_name": "path"}, {"original_string": "protected final transient FileContext fileContext;", "modifier": "protected final transient", "type": "FileContext", "declarator": "fileContext", "var_name": "fileContext"}, {"original_string": "protected static final transient Kryo kryo;", "modifier": "protected static final transient", "type": "Kryo", "declarator": "kryo", "var_name": "kryo"}, {"original_string": "private static final long serialVersionUID = 201404031201L;", "modifier": "private static final", "type": "long", "declarator": "serialVersionUID = 201404031201L", "var_name": "serialVersionUID"}, {"original_string": "private static final Logger logger = LoggerFactory.getLogger(FSStorageAgent.class);", "modifier": "private static final", "type": "Logger", "declarator": "logger = LoggerFactory.getLogger(FSStorageAgent.class)", "var_name": "logger"}], "methods": [{"identifier": "FSStorageAgent", "parameters": "()", "modifiers": "protected", "return": "", "signature": " FSStorageAgent()", "full_signature": "protected  FSStorageAgent()", "class_method_signature": "FSStorageAgent.FSStorageAgent()", "testcase": false, "constructor": true}, {"identifier": "FSStorageAgent", "parameters": "(String path, Configuration conf)", "modifiers": "public", "return": "", "signature": " FSStorageAgent(String path, Configuration conf)", "full_signature": "public  FSStorageAgent(String path, Configuration conf)", "class_method_signature": "FSStorageAgent.FSStorageAgent(String path, Configuration conf)", "testcase": false, "constructor": true}, {"identifier": "save", "parameters": "(Object object, int operatorId, long windowId)", "modifiers": "@SuppressWarnings(\"ThrowFromFinallyBlock\") @Override public", "return": "void", "signature": "void save(Object object, int operatorId, long windowId)", "full_signature": "@SuppressWarnings(\"ThrowFromFinallyBlock\") @Override public void save(Object object, int operatorId, long windowId)", "class_method_signature": "FSStorageAgent.save(Object object, int operatorId, long windowId)", "testcase": false, "constructor": false}, {"identifier": "load", "parameters": "(int operatorId, long windowId)", "modifiers": "@Override public", "return": "Object", "signature": "Object load(int operatorId, long windowId)", "full_signature": "@Override public Object load(int operatorId, long windowId)", "class_method_signature": "FSStorageAgent.load(int operatorId, long windowId)", "testcase": false, "constructor": false}, {"identifier": "delete", "parameters": "(int operatorId, long windowId)", "modifiers": "@Override public", "return": "void", "signature": "void delete(int operatorId, long windowId)", "full_signature": "@Override public void delete(int operatorId, long windowId)", "class_method_signature": "FSStorageAgent.delete(int operatorId, long windowId)", "testcase": false, "constructor": false}, {"identifier": "getWindowIds", "parameters": "(int operatorId)", "modifiers": "@Override public", "return": "long[]", "signature": "long[] getWindowIds(int operatorId)", "full_signature": "@Override public long[] getWindowIds(int operatorId)", "class_method_signature": "FSStorageAgent.getWindowIds(int operatorId)", "testcase": false, "constructor": false}, {"identifier": "store", "parameters": "(OutputStream stream, Object operator)", "modifiers": "public static", "return": "void", "signature": "void store(OutputStream stream, Object operator)", "full_signature": "public static void store(OutputStream stream, Object operator)", "class_method_signature": "FSStorageAgent.store(OutputStream stream, Object operator)", "testcase": false, "constructor": false}, {"identifier": "retrieve", "parameters": "(InputStream stream)", "modifiers": "public static", "return": "Object", "signature": "Object retrieve(InputStream stream)", "full_signature": "public static Object retrieve(InputStream stream)", "class_method_signature": "FSStorageAgent.retrieve(InputStream stream)", "testcase": false, "constructor": false}, {"identifier": "readResolve", "parameters": "()", "modifiers": "public", "return": "Object", "signature": "Object readResolve()", "full_signature": "public Object readResolve()", "class_method_signature": "FSStorageAgent.readResolve()", "testcase": false, "constructor": false}], "file": "common/src/main/java/com/datatorrent/common/util/FSStorageAgent.java"}, "focal_method": {"identifier": "save", "parameters": "(Object object, int operatorId, long windowId)", "modifiers": "@SuppressWarnings(\"ThrowFromFinallyBlock\") @Override public", "return": "void", "body": "@SuppressWarnings(\"ThrowFromFinallyBlock\")\n  @Override\n  public void save(Object object, int operatorId, long windowId) throws IOException\n  {\n    String operatorIdStr = String.valueOf(operatorId);\n    Path lPath = new Path(path + Path.SEPARATOR + operatorIdStr + Path.SEPARATOR + TMP_FILE);\n    String window = Long.toHexString(windowId);\n    boolean stateSaved = false;\n    FSDataOutputStream stream = null;\n    try {\n      stream = fileContext.create(lPath, EnumSet.of(CreateFlag.CREATE, CreateFlag.OVERWRITE),\n        Options.CreateOpts.CreateParent.createParent());\n      store(stream, object);\n      stateSaved = true;\n    } catch (Throwable t) {\n      logger.debug(\"while saving {} {}\", operatorId, window, t);\n      stateSaved = false;\n      throw Throwables.propagate(t);\n    } finally {\n      try {\n        if (stream != null) {\n          stream.close();\n        }\n      } catch (IOException ie) {\n        stateSaved = false;\n        throw new RuntimeException(ie);\n      } finally {\n        if (stateSaved) {\n          logger.debug(\"Saving {}: {}\", operatorId, window);\n          fileContext.rename(lPath, new Path(path + Path.SEPARATOR + operatorIdStr + Path.SEPARATOR + window),\n              Options.Rename.OVERWRITE);\n        }\n      }\n    }\n  }", "signature": "void save(Object object, int operatorId, long windowId)", "full_signature": "@SuppressWarnings(\"ThrowFromFinallyBlock\") @Override public void save(Object object, int operatorId, long windowId)", "class_method_signature": "FSStorageAgent.save(Object object, int operatorId, long windowId)", "testcase": false, "constructor": false, "invocations": ["valueOf", "toHexString", "create", "of", "createParent", "store", "debug", "propagate", "close", "debug", "rename"]}, "repository": {"repo_id": 41348333, "url": "https://github.com/apache/attic-apex-core", "language": "Java", "is_fork": false, "fork_count": 181, "stargazer_count": 346, "size": 14734, "license": "licensed"}}